autoBWF/BWFfileIO.py
autoBWF/__init__.py
autoBWF/autoBWF.py
autoBWF/autobwfconfig.py
autoBWF/autolame.py
autoBWF/autosplice.py
autoBWF/bwf2csv.py
autoBWF/bwf2pbcore.py
autoBWF/export_dialog.py
autoBWF/tabbed.py
autoBWF-3.6.dist-info/AUTHORS.md
autoBWF-3.6.dist-info/LICENSE.txt
autoBWF-3.6.dist-info/METADATA
autoBWF-3.6.dist-info/WHEEL
autoBWF-3.6.dist-info/entry_points.txt
autoBWF-3.6.dist-info/top_level.txt
autoBWF-3.6.dist-info/RECORD
