Metadata-Version: 2.1
Name: autoBWF
Version: 3.6
Summary: Alternative opinionated GUI for FADGI BWFMetaEdit
Home-page: https://github.com/Ukrainian-History/autoBWF
Author: Michael Andrec/Ukrainian History and Education Center
Author-email: m.andrec@ukrhec.org
License: GNU General Public License v3
Classifier: License :: OSI Approved :: GNU General Public License v3 (GPLv3)
Classifier: Natural Language :: English
Classifier: Programming Language :: Python :: 3.6
License-File: LICENSE.txt
License-File: AUTHORS.md
Requires-Dist: appdirs
Requires-Dist: PyQt5
